{"cameraMode":{"drawMode":2,"name":"Shaded Wireframe","section":"Shading Mode"},"sceneLighting":false,"audioPlay":false,"sceneViewState":{"m_AlwaysRefresh":false,"showFog":true,"showSkybox":false,"showFlares":true,"showImageEffects":true,"showParticleSystems":true,"showVisualEffectGraphs":true,"m_FxEnabled":false},"in2DMode":false,"pivot":{"x":0.0,"y":0.75,"z":-0.5},"rotation":{"x":0.3700651526451111,"y":-0.042617104947566989,"z":0.01699751988053322,"w":0.9278701543807983},"size":3.570714235305786,"orthographic":false}